surfing_libs/__init__.py
surfing_libs/excel/__init__.py
surfing_libs/excel/excel.py
surfing_libs/mail/__init__.py
surfing_libs/mail/mail.py
surfing_lib-0.0.1.dist-info/METADATA
surfing_lib-0.0.1.dist-info/WHEEL
surfing_lib-0.0.1.dist-info/top_level.txt
surfing_lib-0.0.1.dist-info/RECORD
