Metadata-Version: 2.1
Name: surfing-lib
Version: 0.0.1
Summary: 公司公用库
Home-page: UNKNOWN
Author: surfing
Author-email: surfing@surfingtech.cn
License: UNKNOWN
Platform: UNKNOWN
Classifier: Programming Language :: Python :: 3
Classifier: License :: OSI Approved :: MIT License
Classifier: Operating System :: OS Independent
